{
  "_key": "2222",
  "teamKey": "1608",
  "invitationCode": "555666",
  "invitational": true,
  "numberOfParticipants": 40,
  "createdTS": "2021-02-08T14: 25: 00.741Z",
  "updatedTS": "2021-02-11T16: 47: 58.945Z",
  "publishedTS": "2021-02-11T16: 47: 58.863Z",
  "generalities": {
    "languages": [
      "en",
      "sv"
    ],
    "title": {
      "en": "ParkApp research study",
      "sv": "ParkApp forskningsstudie"
    },
    "shortDescription": {
      "en": "",
      "sv": ""
    },
    "longDescription": {
      "en": "",
      "sv": ""
    },
    "startDate": "2022-04-28",
    "endDate": "2023-04-28",
    "principalInvestigators": [
      {
        "name": "Per Svenningsson",
        "contact": "Karolinska Institutet, Department of Clinical Neuroscience, Tomtebodavägen 18A, 171 77 Stockholm, Phone: 08-123 673 00 / 08-585 800 00, email: per.svenningsson@ki.se",
        "institution": "Region Stockholm"
      }
    ],
    "institutions": [
      {
        "name": "Region Stockholm",
        "contact": "ASC Torsplan, Solnavägen 1E, 11365 Stockholm",
        "dataAccess": "full",
        "reasonForDataAccess": {
          "en": "Data needed to complete the objectives of the research.",
          "sv": "Data behövs för att slutföra målen för forskningen."
        }
      },
      {
        "name": "Malmö Universitet",
        "contact": "Institutionen för datavetenskap och medieteknik, Nordenskiöldsgatan 1, Malmö",
        "dataAccess": "full",
        "reasonForDataAccess": {
          "en": "Malmö University is responsible for collecting the data through the Mobistudy app and for doing the statistical analysis.",
          "sv": "Malmö Universitet ansvarar för att samla in data via Mobistudy-appen och för att göra den statistiska analysen."
        }
      },
      {
        "name": "Karolinska Institutet",
        "contact": "Department of Clinical Neuroscience, Tomtebodavägen 18A, 171 77 Stockholm",
        "dataAccess": "full",
        "reasonForDataAccess": {
          "en": "Malmö University is responsible for collecting the data through the Mobistudy app and for doing the statistical analysis.",
          "sv": "Malmö Universitet ansvarar för att samla in data via Mobistudy-appen och för att göra den statistiska analysen."
        }
      }
    ]
  },
  "inclusionCriteria": {
    "minAge": 30,
    "maxAge": 100,
    "sex": [
      "male",
      "female",
      "other"
    ],
    "diseases": [],
    "medications": []
  },
  "tasks": [
    {
      "id": 1,
      "type": "tugt",
      "scheduling": {
        "startEvent": "consent",
        "intervalType": "d",
        "untilSecs": 5184000,
        "interval": 1
      },
      "customTitle": {
        "en": "TU&G before medication",
        "sv": "TU&G före medicin"
      }
    },
    {
      "id": 2,
      "type": "tugt",
      "scheduling": {
        "startEvent": "taskExecution",
        "eventTaskId": 1,
        "startDelaySecs": 3600,
        "untilSecs": 43200,
        "intervalType": "d",
        "interval": 1,
        "occurrences": 1
      },
      "customTitle": {
        "en": "TU&G 1h after medication",
        "sv": "TU&G 1t efter medicin"
      }
    },
    {
      "id": 3,
      "type": "vocalization",
      "scheduling": {
        "startEvent": "consent",
        "intervalType": "d",
        "untilSecs": 5184000,
        "interval": 1
      },
      "customTitle": {
        "en": "Voice test before medication",
        "sv": "Vokalisering före medicin"
      }
    },
    {
      "id": 4,
      "type": "vocalization",
      "scheduling": {
        "startEvent": "taskExecution",
        "eventTaskId": 3,
        "startDelaySecs": 3600,
        "untilSecs": 43200,
        "intervalType": "d",
        "interval": 1,
        "occurrences": 1
      },
      "customTitle": {
        "en": "Voice test 1h after medication",
        "sv": "Vokalisering 1t efter medicin"
      }
    },
    {
      "id": 5,
      "type": "holdPhone",
      "scheduling": {
        "startEvent": "consent",
        "intervalType": "d",
        "untilSecs": 5184000,
        "interval": 1
      },
      "customTitle": {
        "en": "Hold-the-phone before medication",
        "sv": "Hålla telefonen före medicin"
      }
    },
    {
      "id": 6,
      "type": "holdPhone",
      "scheduling": {
        "startEvent": "taskExecution",
        "eventTaskId": 5,
        "startDelaySecs": 3600,
        "untilSecs": 43200,
        "intervalType": "d",
        "interval": 1,
        "occurrences": 1
      },
      "customTitle": {
        "en": "Hold-the-phone 1h after medication",
        "sv": "Hålla telefonen 1t efter medicin"
      }
    },
    {
      "id": 7,
      "type": "fingerTapping",
      "scheduling": {
        "startEvent": "consent",
        "intervalType": "d",
        "untilSecs": 5184000,
        "interval": 1
      },
      "customTitle": {
        "en": "Finger tapping before medication",
        "sv": "Fingerfärdighet före medicin"
      }
    },
    {
      "id": 8,
      "type": "fingerTapping",
      "scheduling": {
        "startEvent": "taskExecution",
        "eventTaskId": 7,
        "startDelaySecs": 3600,
        "untilSecs": 43200,
        "intervalType": "d",
        "interval": 1,
        "occurrences": 1
      },
      "customTitle": {
        "en": "Finger tapping 1h after medication",
        "sv": "Fingerfärdighet 1t efter medicin"
      }
    },
    {
      "id": 9,
      "type": "drawing",
      "scheduling": {
        "startEvent": "consent",
        "intervalType": "d",
        "untilSecs": 5184000,
        "interval": 1
      },
      "customTitle": {
        "en": "Drawing test before medication",
        "sv": "Figurtestetet före medicin"
      }
    },
    {
      "id": 10,
      "type": "drawing",
      "scheduling": {
        "startEvent": "taskExecution",
        "eventTaskId": 9,
        "startDelaySecs": 3600,
        "untilSecs": 43200,
        "intervalType": "d",
        "interval": 1,
        "occurrences": 1
      },
      "customTitle": {
        "en": "Drawing test 1h after medication",
        "sv": "Figurtestetet 1t efter medicin"
      }
    },
    {
      "id": 11,
      "type": "form",
      "scheduling": {
        "startEvent": "consent",
        "intervalType": "d",
        "untilSecs": 5184000,
        "interval": 1
      },
      "formKey": "1818",
      "formName": {
        "en": "Daily sleep quality",
        "sv": "Daglig sömnkvalitet"
      }
    },
    {
      "id": 12,
      "type": "form",
      "scheduling": {
        "startEvent": "consent",
        "intervalType": "d",
        "untilSecs": 5184000,
        "interval": 1
      },
      "formKey": "0808",
      "formName": {
        "en": "BDI-2",
        "sv": "BDI-2"
      }
    },
    {
      "id": 13,
      "type": "form",
      "scheduling": {
        "startEvent": "consent",
        "intervalType": "d",
        "untilSecs": 5184000,
        "interval": 1
      },
      "formKey": "7878",
      "formName": {
        "en": "PDSS-2",
        "sv": "PDSS-2"
      }
    },
    {
      "id": 14,
      "type": "form",
      "scheduling": {
        "startEvent": "consent",
        "intervalType": "d",
        "untilSecs": 5184000,
        "interval": 1
      },
      "formKey": "9898",
      "formName": {
        "en": "NMSQuest",
        "sv": "NMSQuest"
      }
    },
    {
      "id": 15,
      "type": "form",
      "scheduling": {
        "startEvent": "consent",
        "intervalType": "d",
        "untilSecs": 5184000,
        "interval": 1
      },
      "formKey": "118118",
      "formName": {
        "en": "PDQ8",
        "sv": "PDQ8"
      }
    },
    {
      "id": 16,
      "type": "form",
      "scheduling": {
        "startEvent": "consent",
        "intervalType": "d",
        "untilSecs": 5184000,
        "interval": 1
      },
      "formKey": "2828",
      "formName": {
        "en": "uMARS",
        "sv": "uMARS"
      }
    },
    {
      "id": 17,
      "type": "form",
      "scheduling": {
        "startEvent": "consent",
        "intervalType": "d",
        "untilSecs": 5184000,
        "interval": 1
      },
      "formKey": "118118",
      "formName": {
        "en": "TAM",
        "sv": "TAM"
      }
    }
  ],
  "consent": {
    "invitation": {
      "en": "Invite",
      "sv": "Invitation"
    },
    "privacyPolicy": {
      "en": "bla bla",
      "sv": "bla bla"
    },
    "taskItems": [
      {
        "description": {
          "en": "I agree to perform a \"Timed Up and Go\" test, once a week -before medication-.",
          "sv": "Jag accepterar att utföra ett \"Timed up and go\" test, en gång i veckan -före medicinering-."
        },
        "taskId": 1
      },
      {
        "description": {
          "en": "I agree to perform a \"Timed Up and Go\" test, once a week -1 hour after medication-.",
          "sv": "Jag accepterar att utföra ett \"Timed up and go\" test, en gång i veckan -1 timme efter medicinering-."
        },
        "taskId": 2
      },
      {
        "description": {
          "en": "I agree to perform a vocalizaiton test, once a week -before medication-.",
          "sv": "Jag accepterar att utföra ett vokaliseringstest, en gång i veckan -före medicinering-."
        },
        "taskId": 3
      },
      {
        "description": {
          "en": "I agree to perform a vocalizaiton test, once a week -1 hour after medication-.",
          "sv": "Jag accepterar att utföra ett vokaliseringstest, en gång i veckan -1 timme efter medicinering-."
        },
        "taskId": 4
      },
      {
        "description": {
          "en": "I agree to perform a \"Hold the phone\" tremor test, once a week -before medication-.",
          "sv": "Jag accepterar att utföra ett \"Håll telefonen\" tremortest, en gång i veckan -före medicinering-."
        },
        "taskId": 5
      },
      {
        "description": {
          "en": "I agree to perform a \"Hold the phone\" test, once a week -1 hour after medication-.",
          "sv": "Jag accepterar att utföra ett \"Håll telefonen\" tremortestet, en gång i veckan -1 timme efter medicinering-."
        },
        "taskId": 6
      },
      {
        "description": {
          "en": "I agree to perform a dexterity \"Finger tapping\" test, once a week -before medication-.",
          "sv": "Jag accepterar att utföra ett fingerfärdighet test, en gång i veckan -före medicinering-."
        },
        "taskId": 7
      },
      {
        "description": {
          "en": "I agree to perform a dexterity \"Finger tapping\" test, once a week -1 hour after medication-.",
          "sv": "Jag accepterar att utföra ett fingerfärdighet test, en gång i veckan -1 timme efter medicinering-."
        },
        "taskId": 8
      },
      {
        "description": {
          "en": "I agree to perform a drawing test, once a week -before medication-.",
          "sv": "Jag accepterar att utföra en ritövning \"Figurtestetet\", en gång i veckan -före medicinering-."
        },
        "taskId": 9
      },
      {
        "description": {
          "en": "I agree to perform a drawing test, once a week -1 hour after medication-.",
          "sv": "Jag accepterar att utföra en ritövning \"Figurtestetet\", en gång i veckan -1 timme efter medicinering-."
        },
        "taskId": 10
      },
      {
        "description": {
          "en": "I agree to answer a daily sleep quality questionnaire, once a day.",
          "sv": "Jag accepterar att besvara en enkät om när du somnar, vaknar och din sömnkvalitet (Daglig sömnkvalitet formulär), varje dag."
        },
        "taskId": 11
      },
      {
        "description": {
          "en": "I agree to answer a questionnaire that identifies signs of depression (Beck Depression Inventory 2), once every month.",
          "sv": "Jag accepterar att besvara en enkät som undersöker tecken på depression (Beck’s depression inventory), en gång i månaden."
        },
        "taskId": 12
      },
      {
        "description": {
          "en": "I agree to answer a questionnaire that provides a sleep scale for Parkinson's disease once a week (Parkinson ́s Disease Sleep Scale), once a week.",
          "sv": "Jag accepterar att besvara en enkät som ger en sömnskala för Parkinsons sjukdom (Parkinson’s disease sleep scale), en gång i veckan."
        },
        "taskId": 13
      },
      {
        "description": {
          "en": "I agree to answer a questionnaire on non-motor symptoms (NMSQuest - Non-Motor Symptoms Questionnaire), once a month.",
          "sv": "Jag accepterar att besvara en enkät om icke-motoriska symtom (NMSQuest - Non-Motor Symptoms Questionnaire), en gång i månaden."
        },
        "taskId": 14
      },
      {
        "description": {
          "en": "I agree to answer a questionnaire on Parkinson's Disease (PDQ-8 - Parkinson's disease Questionnaire-8), once a month.",
          "sv": "Jag accepterar att besvara en enkät om Parkinsons sjukdom (PDQ-8 - Parkinson's disease Questionnaire-8), en gång i månaden."
        },
        "taskId": 15
      },
      {
        "description": {
          "en": "I agree to answer a scale that measures the usability of applications on mobile phones (uMARS - user version of the Mobile Application Rating Scale), once, 3 weeks after I have started the study.",
          "sv": "Jag accepterar att besvara en skala som mäter användbarhet av applikationer på mobiltelefoner (uMARS – user version of the Mobile Application Rating Scale), en gång, 3 veckor efter att jag har påbörjat studien."
        },
        "taskId": 16
      },
      {
        "description": {
          "en": "I agree to answer a questionnaire that measures user acceptance of technology (TAM – Technology Acceptance Model), once, 3 weeks after I have started the study.",
          "sv": "Jag accepterar att besvara en enkät som mäter acceptans av teknologi (TAM – Technology Acceptance Model), en gång, 3 veckor efter att jag har påbörjat studien."
        },
        "taskId": 17
      }
    ],
    "extraItems": [
      {
        "description": {
          "en": "I agree to take part in an interview about the use of the app, at the end of the study.",
          "sv": "Jag går med på att delta i en intervju om användningen av appen, i slutet av studien."
        },
        "optional": true
      },
      {
        "description": {
          "en": "I agree to wear the GENEActiv smart device to measure my activity for 2 months.",
          "sv": "Jag går med på att bära GENEActiv-smartenheten för att mäta min aktivitet i 2 månader."
        },
        "optional": true
      },
      {
        "description": {
          "en": "I agree to undergo 2 Parkinson's related clinical assessments in 2 months.",
          "sv": "Jag samtycker till att genomgå 2 Parkinsonsrelaterade kliniska bedömningar inom 2 månader."
        },
        "optional": false
      }
    ]
  }
}
